fullhdporn_api/__init__.py
fullhdporn_api/fullhdporn_api.py
fullhdporn_api/modules/__init__.py
fullhdporn_api/modules/consts.py
fullhdporn_api/modules/errors.py
fullhdporn_api/tests/__init__.py
fullhdporn_api/tests/test_video.py
fullhdporn_api-1.0.1.dist-info/licenses/LICENSE
fullhdporn_api-1.0.1.dist-info/METADATA
fullhdporn_api-1.0.1.dist-info/WHEEL
fullhdporn_api-1.0.1.dist-info/top_level.txt
fullhdporn_api-1.0.1.dist-info/RECORD
