Metadata-Version: 2.4
Name: fullhdporn_api
Version: 1.0.1
Summary: A Python API for the Porn Site fullhdporn.sex
Author-email: Johannes Habel <EchterAlsFake@proton.me>
License: LGPLv3
Project-URL: Homepage, https://github.com/EchterAlsFake/fullhdporn_api
Classifier: License :: OSI Approved :: GNU Lesser General Public License v3 (LGPLv3)
Classifier: Programming Language :: Python
Requires-Python: >=3.6
License-File: LICENSE
Requires-Dist: bs4
Requires-Dist: eaf_base_api
Requires-Dist: httpx
Requires-Dist: lxml
Requires-Dist: brotli
Requires-Dist: h2
Provides-Extra: av
Requires-Dist: av; extra == "av"
Provides-Extra: ffmpeg
Requires-Dist: ffmpeg-progress-yield; extra == "ffmpeg"
Dynamic: license-file
